py3DCal/__init__.py
py3DCal/data_collection/Calibrator.py
py3DCal/data_collection/__init__.py
py3DCal/data_collection/printers/Printer.py
py3DCal/data_collection/printers/__init__.py
py3DCal/data_collection/printers/Ender3/Ender3.py
py3DCal/data_collection/printers/Ender3/__init__.py
py3DCal/data_collection/sensors/Sensor.py
py3DCal/data_collection/sensors/__init__.py
py3DCal/data_collection/sensors/DIGIT/DIGIT.py
py3DCal/data_collection/sensors/DIGIT/__init__.py
py3DCal/data_collection/sensors/DIGIT/default.csv
py3DCal/data_collection/sensors/GelsightMini/GelsightMini.py
py3DCal/data_collection/sensors/GelsightMini/__init__.py
py3DCal/data_collection/sensors/GelsightMini/default.csv
py3DCal/model_training/__init__.py
py3DCal/model_training/datasets/DIGIT_dataset.py
py3DCal/model_training/datasets/GelSightMini_dataset.py
py3DCal/model_training/datasets/__init__.py
py3DCal/model_training/datasets/split_dataset.py
py3DCal/model_training/datasets/tactile_sensor_dataset.py
py3DCal/model_training/lib/__init__.py
py3DCal/model_training/lib/add_coordinate_embeddings.py
py3DCal/model_training/lib/annotate_dataset.py
py3DCal/model_training/lib/depthmaps.py
py3DCal/model_training/lib/fast_poisson.py
py3DCal/model_training/lib/get_gradient_map.py
py3DCal/model_training/lib/precompute_gradients.py
py3DCal/model_training/lib/train_model.py
py3DCal/model_training/lib/validate_parameters.py
py3DCal/model_training/models/__init__.py
py3DCal/model_training/models/touchnet.py
py3DCal/utils/__init__.py
py3DCal/utils/utils.py
py3dcal-1.0.7.dist-info/LICENSE
py3dcal-1.0.7.dist-info/METADATA
py3dcal-1.0.7.dist-info/WHEEL
py3dcal-1.0.7.dist-info/entry_points.txt
py3dcal-1.0.7.dist-info/top_level.txt
py3dcal-1.0.7.dist-info/RECORD
